responses_server/__init__.py
responses_server/__main__.py
tests/__init__.py
tests/test_server.py
responses_server-0.1.1.dist-info/LICENSE
responses_server-0.1.1.dist-info/METADATA
responses_server-0.1.1.dist-info/WHEEL
responses_server-0.1.1.dist-info/top_level.txt
responses_server-0.1.1.dist-info/RECORD
